hyperdock_wasm/__init__.py
hyperdock_wasm/dock.py
hyperdock_wasm/tool.py
hyperdock_wasm/dto/__init__.py
hyperdock_wasm/dto/browser_script.py
hyperdock_wasm/handlers/__init__.py
hyperdock_wasm/handlers/browser/__init__.py
hyperdock_wasm/handlers/browser/handlers.py
hyperdock_wasm/runtime/__init__.py
hyperdock_wasm/runtime/runtime.py
hyperdock_wasm/runtime/browser/__init__.py
hyperdock_wasm/runtime/browser/invoker.py
hyperdock_wasm/runtime/browser/invoker_browser.py
hyperdock_wasm/runtime/browser/runtime.py
hyperdock_wasm/runtime/browser/script.py
hyperdock_wasm/runtime/browser/templates/__init__.py
hyperdock_wasm/runtime/browser/templates/node.py
hyperdock_wasm/runtime/browser/templates/python.py
hyperdock_wasm/tool_reference/__init__.py
hyperdock_wasm/tool_reference/git.py
hyperdock_wasm/tool_reference/local.py
hyperdock_wasm-0.4.5.dist-info/METADATA
hyperdock_wasm-0.4.5.dist-info/WHEEL
hyperdock_wasm-0.4.5.dist-info/top_level.txt
hyperdock_wasm-0.4.5.dist-info/RECORD
