Metadata-Version: 2.2
Name: hyperdock-wasm
Version: 0.4.5
Summary: Add your description here
Requires-Python: >=3.10
Requires-Dist: fastapi>=0.115.8
Requires-Dist: gitpython>=3.1.44
Requires-Dist: hyperpocket
Requires-Dist: pydantic>=2.10.6
